ebird/pages/__init__.py
ebird/pages/checklists.py
ebird/pages/recent.py
ebird_pages-0.3.0.dist-info/METADATA
ebird_pages-0.3.0.dist-info/WHEEL
ebird_pages-0.3.0.dist-info/top_level.txt
ebird_pages-0.3.0.dist-info/RECORD
