Metadata-Version: 2.4
Name: ebird-pages
Version: 0.3.0
Summary: A python library for scraping data from pages on the eBird web site
Author-email: Stuart MacKay <smackay@flagstonesoftware.com>
License: MIT License
Project-URL: Repository, https://github.com/ebirders/ebird-pages.git
Project-URL: Issues, https://github.com/ebirders/ebird-pages/issues
Project-URL: Changelog, https://github.com/ebirders/ebird-pages/blob/master/CHANGELOG.md
Keywords: eBird,web,scraper
Classifier: Development Status :: 3 - Alpha
Classifier: Environment :: Console
Classifier: Intended Audience :: Science/Research
Classifier: License :: OSI Approved :: MIT License
Classifier: Operating System :: OS Independent
Classifier: Programming Language :: Python
Classifier: Programming Language :: Python :: 3
Classifier: Programming Language :: Python :: 3.8
Classifier: Programming Language :: Python :: 3.9
Classifier: Programming Language :: Python :: 3.10
Classifier: Programming Language :: Python :: 3.11
Classifier: Programming Language :: Python :: 3.12
Classifier: Programming Language :: Python :: Implementation :: CPython
Classifier: Natural Language :: English
Classifier: Topic :: Utilities
Classifier: Topic :: Internet
Requires-Python: >=3.8
Requires-Dist: beautifulsoup4>=4.12.3
Requires-Dist: lxml>=5.3.0
Requires-Dist: requests>=2.32.3
